{
    "task_number": 43,
    "task_name": "228f6490.json",
    "raw_data_path": "tasks_json/228f6490.json",
    "task_summary": {
        "test_input_size": "(10, 10)",
        "test_output_size": "(10, 10)",
        "example_input_sizes": "[(10, 10), (10, 10), (10, 10)]",
        "example_output_sizes": "[(10, 10), (10, 10), (10, 10)]",
        "number_of_examples": 3,
        "test_input_colors": "[1, 0, 1, 0, 1, 1, 0, 1, 0, 0]",
        "test_output_colors": "[1, 0, 1, 0, 1, 1, 0, 1, 0, 0]",
        "nyu_attempt": 18,
        "nyu_successful_1_try": 12,
        "nyu_successful_3_tries": 17
    },
    "description_summary": {
        "number_of_descriptions": 5,
        "average_confidence": 5.4,
        "verification_success_rate": 1.0,
        "average_verification_attempts": 1.0,
        "average_description_synthesis_time": 190.8,
        "average_verification_time": 32.2,
        "descriptions": [
            {
                "description_id": "007e34be-04b1-4bcc-8b3b-377de8faf368",
                "user_id": "21185fa9-4926-4ac2-bcc5-0ee031d0f952",
                "description_input": "In the input, you should see...same grid",
                "description_output_grid_size": "The output grid size...10x10",
                "description_output": "To make the output, you have to...fill in the shapes within the gray area with the color shapes that represent the space.",
                "is_verified": true,
                "confidence": 5,
                "num_verification_attempts": 1,
                "generation": 0,
                "user_num_prior_description_experiences": 4,
                "user_num_prior_build_experiences": 3,
                "description_synthesis_time": 196.0,
                "verification_time": 35.0
            },
            {
                "description_id": "007e34be-04b1-4bcc-8b3b-377de8faf368",
                "user_id": "21185fa9-4926-4ac2-bcc5-0ee031d0f952",
                "description_input": "In the input, you should see...same grid",
                "description_output_grid_size": "The output grid size...10x10",
                "description_output": "To make the output, you have to...fill in the shapes within the gray area with the color shapes that represent the space.",
                "is_verified": true,
                "confidence": 5,
                "num_verification_attempts": 1,
                "generation": 0,
                "user_num_prior_description_experiences": 4,
                "user_num_prior_build_experiences": 3,
                "description_synthesis_time": 196.0,
                "verification_time": 35.0
            },
            {
                "description_id": "007e34be-04b1-4bcc-8b3b-377de8faf368",
                "user_id": "21185fa9-4926-4ac2-bcc5-0ee031d0f952",
                "description_input": "In the input, you should see...same grid",
                "description_output_grid_size": "The output grid size...10x10",
                "description_output": "To make the output, you have to...fill in the shapes within the gray area with the color shapes that represent the space.",
                "is_verified": true,
                "confidence": 5,
                "num_verification_attempts": 1,
                "generation": 0,
                "user_num_prior_description_experiences": 4,
                "user_num_prior_build_experiences": 3,
                "description_synthesis_time": 196.0,
                "verification_time": 35.0
            },
            {
                "description_id": "007e34be-04b1-4bcc-8b3b-377de8faf368",
                "user_id": "21185fa9-4926-4ac2-bcc5-0ee031d0f952",
                "description_input": "In the input, you should see...same grid",
                "description_output_grid_size": "The output grid size...10x10",
                "description_output": "To make the output, you have to...fill in the shapes within the gray area with the color shapes that represent the space.",
                "is_verified": true,
                "confidence": 5,
                "num_verification_attempts": 1,
                "generation": 0,
                "user_num_prior_description_experiences": 4,
                "user_num_prior_build_experiences": 3,
                "description_synthesis_time": 196.0,
                "verification_time": 35.0
            },
            {
                "description_id": "26d31431-131e-4f06-b43d-2240818a6ef3",
                "user_id": "d0a0daaf-ad19-47f8-9812-80cf22edf8e8",
                "description_input": "In the input, you should see...Grey squares with a hole in them, colored boxes that will fit, and some that will not.",
                "description_output_grid_size": "The output grid size...it remains the same.",
                "description_output": "To make the output, you have to...Take a colored shape to fill in the hole for each square. It will only take one shape per square.",
                "is_verified": true,
                "confidence": 7,
                "num_verification_attempts": 1,
                "generation": 1,
                "user_num_prior_description_experiences": 4,
                "user_num_prior_build_experiences": 3,
                "description_synthesis_time": 170.0,
                "verification_time": 21.0
            }
        ]
    },
    "annotated_phrases": [
        {
            "phrase_number": 243,
            "phrase_kind": "input",
            "nth_phrase_in_paragraph": 1,
            "phrase": "same grid",
            "tag_procedure": 0,
            "tag_metaphor": 0,
            "tag_clarification": 0,
            "tag_example": 0,
            "tag_array": 0,
            "tag_validation": 0,
            "tag_loop": 0,
            "tag_start_stop": 0,
            "tag_conditional": 0,
            "tag_logic": 1,
            "tag_framing": 0,
            "tag_spatial_relation": 0,
            "tag_physical_interaction": 0,
            "tag_contact_transform": 0,
            "tag_affine_transform": 0,
            "tag_visual_graphical_transform": 0,
            "tag_object_detection": 0
        },
        {
            "phrase_number": 244,
            "phrase_kind": "grid_size",
            "nth_phrase_in_paragraph": 1,
            "phrase": "10x10",
            "tag_procedure": 0,
            "tag_metaphor": 0,
            "tag_clarification": 0,
            "tag_example": 0,
            "tag_array": 0,
            "tag_validation": 0,
            "tag_loop": 0,
            "tag_start_stop": 0,
            "tag_conditional": 0,
            "tag_logic": 0,
            "tag_framing": 0,
            "tag_spatial_relation": 0,
            "tag_physical_interaction": 0,
            "tag_contact_transform": 0,
            "tag_affine_transform": 0,
            "tag_visual_graphical_transform": 0,
            "tag_object_detection": 1
        },
        {
            "phrase_number": 245,
            "phrase_kind": "output",
            "nth_phrase_in_paragraph": 1,
            "phrase": "fill in the shapes within the gray area with the color shapes that represent the space.",
            "tag_procedure": 1,
            "tag_metaphor": 1,
            "tag_clarification": 0,
            "tag_example": 0,
            "tag_array": 1,
            "tag_validation": 0,
            "tag_loop": 1,
            "tag_start_stop": 0,
            "tag_conditional": 0,
            "tag_logic": 0,
            "tag_framing": 0,
            "tag_spatial_relation": 1,
            "tag_physical_interaction": 0,
            "tag_contact_transform": 0,
            "tag_affine_transform": 0,
            "tag_visual_graphical_transform": 1,
            "tag_object_detection": 1
        }
    ]
}