{
    "task_number": 83,
    "task_name": "3bd67248.json",
    "raw_data_path": "tasks_json/3bd67248.json",
    "task_summary": {
        "test_input_size": "(10, 10)",
        "test_output_size": "(10, 10)",
        "example_input_sizes": "[(15, 15), (3, 3), (7, 7)]",
        "example_output_sizes": "[(15, 15), (3, 3), (7, 7)]",
        "number_of_examples": 3,
        "test_input_colors": "[1, 0, 0, 1, 0, 0, 0, 0, 0, 0]",
        "test_output_colors": "[1, 0, 1, 1, 1, 0, 0, 0, 0, 0]",
        "nyu_attempt": 0,
        "nyu_successful_1_try": 0,
        "nyu_successful_3_tries": 0
    },
    "description_summary": {
        "number_of_descriptions": 6,
        "average_confidence": 6.666666666666667,
        "verification_success_rate": 0.5,
        "average_verification_attempts": 2.1666666666666665,
        "average_description_synthesis_time": 196.33333333333334,
        "average_verification_time": 64.16666666666667,
        "descriptions": [
            {
                "description_id": "0983c310-7616-443c-8c75-e59056fc0cba",
                "user_id": "de16adcb-eed7-4a1b-983b-f25fd2bc400f",
                "description_input": "In the input, you should see...Two edge grid use to center of one grid.",
                "description_output_grid_size": "The output grid size...Two edge grid use to center of one grid.",
                "description_output": "To make the output, you have to...Two edge grid use to center of one grid.",
                "is_verified": false,
                "confidence": 0,
                "num_verification_attempts": 3,
                "generation": 1,
                "user_num_prior_description_experiences": 3,
                "user_num_prior_build_experiences": 1,
                "description_synthesis_time": 97.0,
                "verification_time": 218.0
            },
            {
                "description_id": "1fd287b6-4f3a-4697-ae7f-aae9e9ec6ccb",
                "user_id": "933c9774-791c-494b-804e-eb9b498d9281",
                "description_input": "In the input, you should see... a colored line on the left side of the grid.",
                "description_output_grid_size": "The output grid size... is the same as the input grid.",
                "description_output": "To make the output, you have to... copy the input grid. Fill in all of the squares on the bottom row of the grid with yellow. Then draw a red line diagonal from the black square in the bottom left up to the top right of the grid. Do not change the bottom left color when you draw the yellow and red lines; the yellow and red lines each begin in the second column of the grid.",
                "is_verified": true,
                "confidence": 8,
                "num_verification_attempts": 1,
                "generation": 3,
                "user_num_prior_description_experiences": 6,
                "user_num_prior_build_experiences": 5,
                "description_synthesis_time": 168.0,
                "verification_time": 29.0
            },
            {
                "description_id": "9476b493-dedc-4c90-b162-3e2d5f635237",
                "user_id": "1cde2893-07ea-40e7-bb57-42f83240bc75",
                "description_input": "In the input, you should see... two colored line",
                "description_output_grid_size": "The output grid size...is the same",
                "description_output": "To make the output, you have to... add a red diagonal line that start in the first black square diagonal to where the colored lines meet",
                "is_verified": false,
                "confidence": 0,
                "num_verification_attempts": 3,
                "generation": 0,
                "user_num_prior_description_experiences": 2,
                "user_num_prior_build_experiences": 1,
                "description_synthesis_time": 128.0,
                "verification_time": 46.0
            },
            {
                "description_id": "ca453133-ceb0-4f23-aa64-736891b9d744",
                "user_id": "10c2f6a9-488c-4b93-ae34-5649ac377e72",
                "description_input": "In the input, you should see...good experiment",
                "description_output_grid_size": "The output grid size...good experiment",
                "description_output": "To make the output, you have to...good experiment",
                "is_verified": false,
                "confidence": 0,
                "num_verification_attempts": 3,
                "generation": 4,
                "user_num_prior_description_experiences": 2,
                "user_num_prior_build_experiences": 8,
                "description_synthesis_time": 35.0,
                "verification_time": 36.0
            },
            {
                "description_id": "d2808934-6f1c-4a56-b740-df38370d2ca0",
                "user_id": "7a688d32-36bf-4657-bcfd-36e76b326943",
                "description_input": "In the input, you should see...colored squares on the left side, taking up the entire left side of the input.",
                "description_output_grid_size": "The output grid size... should be the same as the input.",
                "description_output": "To make the output, you have to... make a yellow line across the bottom horizontal. You then have to make an orange line starting from the bottom left and ending at the top right square. This orange line should go through the entire grid.",
                "is_verified": true,
                "confidence": 2,
                "num_verification_attempts": 2,
                "generation": 2,
                "user_num_prior_description_experiences": 1,
                "user_num_prior_build_experiences": 4,
                "description_synthesis_time": 162.0,
                "verification_time": 29.0
            },
            {
                "description_id": "ffb952c5-010f-4364-b07a-368c42bd5273",
                "user_id": "8bf24ee0-cca0-4c82-a691-de451ea8ad36",
                "description_input": "In the input, you should see... black background with a colored vertical line to the left",
                "description_output_grid_size": "The output grid size... is identical.",
                "description_output": "To make the output, you have to... you need to make a yellow line perpendicular to the line located at the left half and then you draw a diagonal red line starting at the intersecting between both lines.",
                "is_verified": true,
                "confidence": 10,
                "num_verification_attempts": 1,
                "generation": 5,
                "user_num_prior_description_experiences": 2,
                "user_num_prior_build_experiences": 5,
                "description_synthesis_time": 588.0,
                "verification_time": 27.0
            }
        ]
    },
    "annotated_phrases": [
        {
            "phrase_number": 454,
            "phrase_kind": "input",
            "nth_phrase_in_paragraph": 1,
            "phrase": "a colored line on the left side of the grid.",
            "tag_procedure": 0,
            "tag_metaphor": 0,
            "tag_clarification": 0,
            "tag_example": 0,
            "tag_array": 0,
            "tag_validation": 0,
            "tag_loop": 0,
            "tag_start_stop": 0,
            "tag_conditional": 0,
            "tag_logic": 0,
            "tag_framing": 0,
            "tag_spatial_relation": 0,
            "tag_physical_interaction": 0,
            "tag_contact_transform": 0,
            "tag_affine_transform": 0,
            "tag_visual_graphical_transform": 0,
            "tag_object_detection": 0
        },
        {
            "phrase_number": 455,
            "phrase_kind": "grid_size",
            "nth_phrase_in_paragraph": 1,
            "phrase": "is the same as the input grid.",
            "tag_procedure": 0,
            "tag_metaphor": 0,
            "tag_clarification": 0,
            "tag_example": 0,
            "tag_array": 0,
            "tag_validation": 0,
            "tag_loop": 0,
            "tag_start_stop": 0,
            "tag_conditional": 0,
            "tag_logic": 0,
            "tag_framing": 0,
            "tag_spatial_relation": 0,
            "tag_physical_interaction": 0,
            "tag_contact_transform": 0,
            "tag_affine_transform": 0,
            "tag_visual_graphical_transform": 0,
            "tag_object_detection": 0
        },
        {
            "phrase_number": 456,
            "phrase_kind": "output",
            "nth_phrase_in_paragraph": 1,
            "phrase": "copy the input grid.",
            "tag_procedure": 0,
            "tag_metaphor": 0,
            "tag_clarification": 0,
            "tag_example": 0,
            "tag_array": 0,
            "tag_validation": 0,
            "tag_loop": 0,
            "tag_start_stop": 0,
            "tag_conditional": 0,
            "tag_logic": 0,
            "tag_framing": 0,
            "tag_spatial_relation": 0,
            "tag_physical_interaction": 0,
            "tag_contact_transform": 0,
            "tag_affine_transform": 0,
            "tag_visual_graphical_transform": 0,
            "tag_object_detection": 0
        },
        {
            "phrase_number": 457,
            "phrase_kind": "output",
            "nth_phrase_in_paragraph": 2,
            "phrase": "Fill in all of the squares on the bottom row of the grid with yellow.",
            "tag_procedure": 0,
            "tag_metaphor": 0,
            "tag_clarification": 0,
            "tag_example": 0,
            "tag_array": 0,
            "tag_validation": 0,
            "tag_loop": 0,
            "tag_start_stop": 0,
            "tag_conditional": 0,
            "tag_logic": 0,
            "tag_framing": 0,
            "tag_spatial_relation": 0,
            "tag_physical_interaction": 0,
            "tag_contact_transform": 0,
            "tag_affine_transform": 0,
            "tag_visual_graphical_transform": 0,
            "tag_object_detection": 0
        },
        {
            "phrase_number": 458,
            "phrase_kind": "output",
            "nth_phrase_in_paragraph": 3,
            "phrase": "Then draw a red line diagonal from the black square in the bottom left up to the top right of the grid.",
            "tag_procedure": 0,
            "tag_metaphor": 0,
            "tag_clarification": 0,
            "tag_example": 0,
            "tag_array": 0,
            "tag_validation": 0,
            "tag_loop": 0,
            "tag_start_stop": 0,
            "tag_conditional": 0,
            "tag_logic": 0,
            "tag_framing": 0,
            "tag_spatial_relation": 0,
            "tag_physical_interaction": 0,
            "tag_contact_transform": 0,
            "tag_affine_transform": 0,
            "tag_visual_graphical_transform": 0,
            "tag_object_detection": 0
        },
        {
            "phrase_number": 459,
            "phrase_kind": "output",
            "nth_phrase_in_paragraph": 4,
            "phrase": "Do not change the bottom left color when you draw the yellow and red lines; the yellow and red lines each begin in the second column of the grid.",
            "tag_procedure": 0,
            "tag_metaphor": 0,
            "tag_clarification": 0,
            "tag_example": 0,
            "tag_array": 0,
            "tag_validation": 0,
            "tag_loop": 0,
            "tag_start_stop": 0,
            "tag_conditional": 0,
            "tag_logic": 0,
            "tag_framing": 0,
            "tag_spatial_relation": 0,
            "tag_physical_interaction": 0,
            "tag_contact_transform": 0,
            "tag_affine_transform": 0,
            "tag_visual_graphical_transform": 0,
            "tag_object_detection": 0
        }
    ]
}