{
    "task_number": 111,
    "task_name": "4938f0c2.json",
    "raw_data_path": "tasks_json/4938f0c2.json",
    "task_summary": {
        "test_input_size": "(14, 18)",
        "test_output_size": "(14, 18)",
        "example_input_sizes": "[(30, 20), (10, 10), (14, 12)]",
        "example_output_sizes": "[(30, 20), (10, 10), (14, 12)]",
        "number_of_examples": 3,
        "test_input_colors": "[1, 0, 1, 1, 0, 0, 0, 0, 0, 0]",
        "test_output_colors": "[1, 0, 1, 1, 0, 0, 0, 0, 0, 0]",
        "nyu_attempt": 0,
        "nyu_successful_1_try": 0,
        "nyu_successful_3_tries": 0
    },
    "description_summary": {
        "number_of_descriptions": 7,
        "average_confidence": 9.285714285714286,
        "verification_success_rate": 1.0,
        "average_verification_attempts": 1.0,
        "average_description_synthesis_time": 177.85714285714286,
        "average_verification_time": 67.42857142857143,
        "descriptions": [
            {
                "description_id": "9426dd3c-1819-4246-b007-9fd8d340e4b4",
                "user_id": "0e487a2e-432c-4cff-ba6a-ab5b417194d5",
                "description_input": "In the input, you should see...a green cube consisting of four green squares in the middle, surrounded by either one, two, three, or four red square designs on a black tile background.",
                "description_output_grid_size": "The output grid size...is similar.",
                "description_output": "To make the output, you have to...use the same red design to create a symmetrical design surrounding the green cube. The red design should hit all four corners, the same as the first (second or third) design. If there are already four designs present, then simply copy the entire grid and do not change anything.",
                "is_verified": true,
                "confidence": 5,
                "num_verification_attempts": 1,
                "generation": 0,
                "user_num_prior_description_experiences": 3,
                "user_num_prior_build_experiences": 0,
                "description_synthesis_time": 369.0,
                "verification_time": 106.0
            },
            {
                "description_id": "fe8bea1c-d255-433e-8e7f-1c151b3b6a98",
                "user_id": "47465cd2-1015-4133-901a-17d56be060cc",
                "description_input": "In the input, you should see...a design pattern",
                "description_output_grid_size": "The output grid size... is similar",
                "description_output": "To make the output, you have to...correlate the design until you have a pattern on all 4 corners of the cube",
                "is_verified": true,
                "confidence": 10,
                "num_verification_attempts": 1,
                "generation": 1,
                "user_num_prior_description_experiences": 5,
                "user_num_prior_build_experiences": 0,
                "description_synthesis_time": 146.0,
                "verification_time": 61.0
            },
            {
                "description_id": "fe8bea1c-d255-433e-8e7f-1c151b3b6a98",
                "user_id": "47465cd2-1015-4133-901a-17d56be060cc",
                "description_input": "In the input, you should see...a design pattern",
                "description_output_grid_size": "The output grid size... is similar",
                "description_output": "To make the output, you have to...correlate the design until you have a pattern on all 4 corners of the cube",
                "is_verified": true,
                "confidence": 10,
                "num_verification_attempts": 1,
                "generation": 1,
                "user_num_prior_description_experiences": 5,
                "user_num_prior_build_experiences": 0,
                "description_synthesis_time": 146.0,
                "verification_time": 61.0
            },
            {
                "description_id": "fe8bea1c-d255-433e-8e7f-1c151b3b6a98",
                "user_id": "47465cd2-1015-4133-901a-17d56be060cc",
                "description_input": "In the input, you should see...a design pattern",
                "description_output_grid_size": "The output grid size... is similar",
                "description_output": "To make the output, you have to...correlate the design until you have a pattern on all 4 corners of the cube",
                "is_verified": true,
                "confidence": 10,
                "num_verification_attempts": 1,
                "generation": 1,
                "user_num_prior_description_experiences": 5,
                "user_num_prior_build_experiences": 0,
                "description_synthesis_time": 146.0,
                "verification_time": 61.0
            },
            {
                "description_id": "fe8bea1c-d255-433e-8e7f-1c151b3b6a98",
                "user_id": "47465cd2-1015-4133-901a-17d56be060cc",
                "description_input": "In the input, you should see...a design pattern",
                "description_output_grid_size": "The output grid size... is similar",
                "description_output": "To make the output, you have to...correlate the design until you have a pattern on all 4 corners of the cube",
                "is_verified": true,
                "confidence": 10,
                "num_verification_attempts": 1,
                "generation": 1,
                "user_num_prior_description_experiences": 5,
                "user_num_prior_build_experiences": 0,
                "description_synthesis_time": 146.0,
                "verification_time": 61.0
            },
            {
                "description_id": "fe8bea1c-d255-433e-8e7f-1c151b3b6a98",
                "user_id": "47465cd2-1015-4133-901a-17d56be060cc",
                "description_input": "In the input, you should see...a design pattern",
                "description_output_grid_size": "The output grid size... is similar",
                "description_output": "To make the output, you have to...correlate the design until you have a pattern on all 4 corners of the cube",
                "is_verified": true,
                "confidence": 10,
                "num_verification_attempts": 1,
                "generation": 1,
                "user_num_prior_description_experiences": 5,
                "user_num_prior_build_experiences": 0,
                "description_synthesis_time": 146.0,
                "verification_time": 61.0
            },
            {
                "description_id": "fe8bea1c-d255-433e-8e7f-1c151b3b6a98",
                "user_id": "47465cd2-1015-4133-901a-17d56be060cc",
                "description_input": "In the input, you should see...a design pattern",
                "description_output_grid_size": "The output grid size... is similar",
                "description_output": "To make the output, you have to...correlate the design until you have a pattern on all 4 corners of the cube",
                "is_verified": true,
                "confidence": 10,
                "num_verification_attempts": 1,
                "generation": 1,
                "user_num_prior_description_experiences": 5,
                "user_num_prior_build_experiences": 0,
                "description_synthesis_time": 146.0,
                "verification_time": 61.0
            }
        ]
    },
    "annotated_phrases": [
        {
            "phrase_number": 628,
            "phrase_kind": "input",
            "nth_phrase_in_paragraph": 1,
            "phrase": "a design pattern",
            "tag_procedure": 0,
            "tag_metaphor": 0,
            "tag_clarification": 0,
            "tag_example": 0,
            "tag_array": 0,
            "tag_validation": 0,
            "tag_loop": 0,
            "tag_start_stop": 0,
            "tag_conditional": 0,
            "tag_logic": 0,
            "tag_framing": 0,
            "tag_spatial_relation": 0,
            "tag_physical_interaction": 0,
            "tag_contact_transform": 0,
            "tag_affine_transform": 0,
            "tag_visual_graphical_transform": 0,
            "tag_object_detection": 0
        },
        {
            "phrase_number": 629,
            "phrase_kind": "grid_size",
            "nth_phrase_in_paragraph": 1,
            "phrase": "is similar",
            "tag_procedure": 0,
            "tag_metaphor": 0,
            "tag_clarification": 0,
            "tag_example": 0,
            "tag_array": 0,
            "tag_validation": 0,
            "tag_loop": 0,
            "tag_start_stop": 0,
            "tag_conditional": 0,
            "tag_logic": 0,
            "tag_framing": 0,
            "tag_spatial_relation": 0,
            "tag_physical_interaction": 0,
            "tag_contact_transform": 0,
            "tag_affine_transform": 0,
            "tag_visual_graphical_transform": 0,
            "tag_object_detection": 0
        },
        {
            "phrase_number": 630,
            "phrase_kind": "output",
            "nth_phrase_in_paragraph": 1,
            "phrase": "correlate the design until you have a pattern on all 4 corners of the cube",
            "tag_procedure": 0,
            "tag_metaphor": 0,
            "tag_clarification": 0,
            "tag_example": 0,
            "tag_array": 0,
            "tag_validation": 0,
            "tag_loop": 0,
            "tag_start_stop": 0,
            "tag_conditional": 0,
            "tag_logic": 0,
            "tag_framing": 0,
            "tag_spatial_relation": 0,
            "tag_physical_interaction": 0,
            "tag_contact_transform": 0,
            "tag_affine_transform": 0,
            "tag_visual_graphical_transform": 0,
            "tag_object_detection": 0
        }
    ]
}