{
    "task_number": 365,
    "task_name": "e6721834.json",
    "raw_data_path": "tasks_json/e6721834.json",
    "task_summary": {
        "test_input_size": "(12, 24)",
        "test_output_size": "(12, 12)",
        "example_input_sizes": "[(17, 30), (20, 11), (16, 10)]",
        "example_output_sizes": "[(17, 15), (10, 11), (8, 10)]",
        "number_of_examples": 3,
        "test_input_colors": "[0, 1, 1, 0, 1, 0, 0, 0, 1, 0]",
        "test_output_colors": "[0, 1, 0, 0, 1, 0, 0, 0, 1, 0]",
        "nyu_attempt": 0,
        "nyu_successful_1_try": 0,
        "nyu_successful_3_tries": 0
    },
    "description_summary": {
        "number_of_descriptions": 5,
        "average_confidence": 5.4,
        "verification_success_rate": 1.0,
        "average_verification_attempts": 1.0,
        "average_description_synthesis_time": 604.4,
        "average_verification_time": 115.2,
        "descriptions": [
            {
                "description_id": "154158b7-8f24-4556-bc32-5cdcaa1fd42e",
                "user_id": "46f3a2e7-cf2a-4a9c-a59d-d3bb99f36096",
                "description_input": "In the input, you should see....a large grid with two different colors.",
                "description_output_grid_size": "The output grid size...is one half the size of the original grid with the same orientation",
                "description_output": "To make the output, you have to...change the output grid to the background color that does not include the two boxes.  Next place the colored boxes on the grid where the interior colored boxes match.",
                "is_verified": true,
                "confidence": 6,
                "num_verification_attempts": 1,
                "generation": 0,
                "user_num_prior_description_experiences": 0,
                "user_num_prior_build_experiences": 0,
                "description_synthesis_time": 437.0,
                "verification_time": 97.0
            },
            {
                "description_id": "d885b0af-4fe9-424d-a70e-6953e50a5d8f",
                "user_id": "29eda9d0-baff-4eca-ad5a-11dc7d788ddc",
                "description_input": "In the input, you should see...2 sections next to each other, each with a different background color. One section has single squares. The other has the same squares but surrounded by other squares in different color.",
                "description_output_grid_size": "The output grid size...is the same as the section with single squares.",
                "description_output": "To make the output, you have to...Using the section with the single squares as starting point, look on the other section for the corresponding squares and copy the squares surrounding the single squares onto the output",
                "is_verified": true,
                "confidence": 3,
                "num_verification_attempts": 1,
                "generation": 1,
                "user_num_prior_description_experiences": 4,
                "user_num_prior_build_experiences": 3,
                "description_synthesis_time": 1754.0,
                "verification_time": 179.0
            },
            {
                "description_id": "dcbef428-4939-4873-9da0-639453718111",
                "user_id": "0b218ee8-0995-4601-9040-4e04608019a6",
                "description_input": "In the input, you should see...a large grid with two different colors. One grid will have individual colored squares. The other grid will have colored squares surrounded by another color.",
                "description_output_grid_size": "The output grid size...Is one half the size of the original grid with the same orientation.",
                "description_output": "To make the output, you have to...Copy the grid that has the individual colored squares only. Look at the grid that was not used and create the same colored shapes around the individual squares on the grid. They should be the same colors, shapes, and number of squares.",
                "is_verified": true,
                "confidence": 6,
                "num_verification_attempts": 1,
                "generation": 2,
                "user_num_prior_description_experiences": 3,
                "user_num_prior_build_experiences": 4,
                "description_synthesis_time": 277.0,
                "verification_time": 100.0
            },
            {
                "description_id": "dcbef428-4939-4873-9da0-639453718111",
                "user_id": "0b218ee8-0995-4601-9040-4e04608019a6",
                "description_input": "In the input, you should see...a large grid with two different colors. One grid will have individual colored squares. The other grid will have colored squares surrounded by another color.",
                "description_output_grid_size": "The output grid size...Is one half the size of the original grid with the same orientation.",
                "description_output": "To make the output, you have to...Copy the grid that has the individual colored squares only. Look at the grid that was not used and create the same colored shapes around the individual squares on the grid. They should be the same colors, shapes, and number of squares.",
                "is_verified": true,
                "confidence": 6,
                "num_verification_attempts": 1,
                "generation": 2,
                "user_num_prior_description_experiences": 3,
                "user_num_prior_build_experiences": 4,
                "description_synthesis_time": 277.0,
                "verification_time": 100.0
            },
            {
                "description_id": "dcbef428-4939-4873-9da0-639453718111",
                "user_id": "0b218ee8-0995-4601-9040-4e04608019a6",
                "description_input": "In the input, you should see...a large grid with two different colors. One grid will have individual colored squares. The other grid will have colored squares surrounded by another color.",
                "description_output_grid_size": "The output grid size...Is one half the size of the original grid with the same orientation.",
                "description_output": "To make the output, you have to...Copy the grid that has the individual colored squares only. Look at the grid that was not used and create the same colored shapes around the individual squares on the grid. They should be the same colors, shapes, and number of squares.",
                "is_verified": true,
                "confidence": 6,
                "num_verification_attempts": 1,
                "generation": 2,
                "user_num_prior_description_experiences": 3,
                "user_num_prior_build_experiences": 4,
                "description_synthesis_time": 277.0,
                "verification_time": 100.0
            }
        ]
    },
    "annotated_phrases": [
        {
            "phrase_number": 2115,
            "phrase_kind": "input",
            "nth_phrase_in_paragraph": 1,
            "phrase": "a large grid with two different colors.",
            "tag_procedure": 0,
            "tag_metaphor": 0,
            "tag_clarification": 0,
            "tag_example": 0,
            "tag_array": 0,
            "tag_validation": 0,
            "tag_loop": 0,
            "tag_start_stop": 0,
            "tag_conditional": 0,
            "tag_logic": 0,
            "tag_framing": 0,
            "tag_spatial_relation": 0,
            "tag_physical_interaction": 0,
            "tag_contact_transform": 0,
            "tag_affine_transform": 0,
            "tag_visual_graphical_transform": 0,
            "tag_object_detection": 0
        },
        {
            "phrase_number": 2116,
            "phrase_kind": "input",
            "nth_phrase_in_paragraph": 2,
            "phrase": "One grid will have individual colored squares.",
            "tag_procedure": 0,
            "tag_metaphor": 0,
            "tag_clarification": 0,
            "tag_example": 0,
            "tag_array": 0,
            "tag_validation": 0,
            "tag_loop": 0,
            "tag_start_stop": 0,
            "tag_conditional": 0,
            "tag_logic": 0,
            "tag_framing": 0,
            "tag_spatial_relation": 0,
            "tag_physical_interaction": 0,
            "tag_contact_transform": 0,
            "tag_affine_transform": 0,
            "tag_visual_graphical_transform": 0,
            "tag_object_detection": 0
        },
        {
            "phrase_number": 2117,
            "phrase_kind": "input",
            "nth_phrase_in_paragraph": 3,
            "phrase": "The other grid will have colored squares surrounded by another color.",
            "tag_procedure": 0,
            "tag_metaphor": 0,
            "tag_clarification": 0,
            "tag_example": 0,
            "tag_array": 0,
            "tag_validation": 0,
            "tag_loop": 0,
            "tag_start_stop": 0,
            "tag_conditional": 0,
            "tag_logic": 0,
            "tag_framing": 0,
            "tag_spatial_relation": 0,
            "tag_physical_interaction": 0,
            "tag_contact_transform": 0,
            "tag_affine_transform": 0,
            "tag_visual_graphical_transform": 0,
            "tag_object_detection": 0
        },
        {
            "phrase_number": 2118,
            "phrase_kind": "grid_size",
            "nth_phrase_in_paragraph": 1,
            "phrase": "Is one half the size of the original grid with the same orientation.",
            "tag_procedure": 0,
            "tag_metaphor": 0,
            "tag_clarification": 0,
            "tag_example": 0,
            "tag_array": 0,
            "tag_validation": 0,
            "tag_loop": 0,
            "tag_start_stop": 0,
            "tag_conditional": 0,
            "tag_logic": 0,
            "tag_framing": 0,
            "tag_spatial_relation": 0,
            "tag_physical_interaction": 0,
            "tag_contact_transform": 0,
            "tag_affine_transform": 0,
            "tag_visual_graphical_transform": 0,
            "tag_object_detection": 0
        },
        {
            "phrase_number": 2119,
            "phrase_kind": "output",
            "nth_phrase_in_paragraph": 1,
            "phrase": "Copy the grid that has the individual colored squares only.",
            "tag_procedure": 0,
            "tag_metaphor": 0,
            "tag_clarification": 0,
            "tag_example": 0,
            "tag_array": 0,
            "tag_validation": 0,
            "tag_loop": 0,
            "tag_start_stop": 0,
            "tag_conditional": 0,
            "tag_logic": 0,
            "tag_framing": 0,
            "tag_spatial_relation": 0,
            "tag_physical_interaction": 0,
            "tag_contact_transform": 0,
            "tag_affine_transform": 0,
            "tag_visual_graphical_transform": 0,
            "tag_object_detection": 0
        },
        {
            "phrase_number": 2120,
            "phrase_kind": "output",
            "nth_phrase_in_paragraph": 2,
            "phrase": "Look at the grid that was not used and create the same colored shapes around the individual squares on the grid.",
            "tag_procedure": 0,
            "tag_metaphor": 0,
            "tag_clarification": 0,
            "tag_example": 0,
            "tag_array": 0,
            "tag_validation": 0,
            "tag_loop": 0,
            "tag_start_stop": 0,
            "tag_conditional": 0,
            "tag_logic": 0,
            "tag_framing": 0,
            "tag_spatial_relation": 0,
            "tag_physical_interaction": 0,
            "tag_contact_transform": 0,
            "tag_affine_transform": 0,
            "tag_visual_graphical_transform": 0,
            "tag_object_detection": 0
        },
        {
            "phrase_number": 2121,
            "phrase_kind": "output",
            "nth_phrase_in_paragraph": 3,
            "phrase": "They should be the same colors, shapes, and number of squares.",
            "tag_procedure": 0,
            "tag_metaphor": 0,
            "tag_clarification": 0,
            "tag_example": 0,
            "tag_array": 0,
            "tag_validation": 0,
            "tag_loop": 0,
            "tag_start_stop": 0,
            "tag_conditional": 0,
            "tag_logic": 0,
            "tag_framing": 0,
            "tag_spatial_relation": 0,
            "tag_physical_interaction": 0,
            "tag_contact_transform": 0,
            "tag_affine_transform": 0,
            "tag_visual_graphical_transform": 0,
            "tag_object_detection": 0
        }
    ]
}